MANIFEST.in
README.md
requirements.txt
setup.py
quadratic_programs/__init__.py
quadratic_programs/exceptions.py
quadratic_programs/helpers.py
quadratic_programs/permute_sparse_pauli_op.py
quadratic_programs/spsa.py
quadratic_programs/version.py
quadratic_programs.egg-info/PKG-INFO
quadratic_programs.egg-info/SOURCES.txt
quadratic_programs.egg-info/dependency_links.txt
quadratic_programs.egg-info/not-zip-safe
quadratic_programs.egg-info/requires.txt
quadratic_programs.egg-info/top_level.txt
quadratic_programs/quadratic_program/__init__.py
quadratic_programs/quadratic_program/constraint.py
quadratic_programs/quadratic_program/exceptions.py
quadratic_programs/quadratic_program/linear_constraint.py
quadratic_programs/quadratic_program/linear_expression.py
quadratic_programs/quadratic_program/prettyprint.py
quadratic_programs/quadratic_program/quadratic_constraint.py
quadratic_programs/quadratic_program/quadratic_expression.py
quadratic_programs/quadratic_program/quadratic_objective.py
quadratic_programs/quadratic_program/quadratic_program.py
quadratic_programs/quadratic_program/quadratic_program_element.py
quadratic_programs/quadratic_program/variable.py
quadratic_programs/quadratic_program/passes/__init__.py
quadratic_programs/quadratic_program/passes/eval_solution.py
quadratic_programs/quadratic_program/passes/flip_problem_sense.py
quadratic_programs/quadratic_program/passes/inequality_to_equality.py
quadratic_programs/quadratic_program/passes/integer_to_binary.py
quadratic_programs/quadratic_program/passes/linear_equality_to_penalty.py
quadratic_programs/quadratic_program/passes/linear_inequality_to_penalty.py
quadratic_programs/quadratic_program/passes/quadratic_program_converter.py
quadratic_programs/quadratic_program/passes/quadratic_program_to_qubo.py
quadratic_programs/quadratic_program/passes/qubo_unroller.py
quadratic_programs/quadratic_program/passes/validation.py
quadratic_programs/translators/__init__.py
quadratic_programs/translators/docplex_mp_to_qp.py
quadratic_programs/translators/qubo_to_sparse_pauli_op.py
quadratic_programs/workflows/__init__.py
quadratic_programs/workflows/fulqrum.py
quadratic_programs/workflows/quadratic_program_workflows.py