Metadata-Version: 2.1
Name: quadratic-programs
Version: 0.1.1
Summary: Quadratic functions
Home-page: 
Author: IBM Quantum
Author-email: paul.nation@ibm.com
License: Apache 2.0
Classifier: License :: Other/Proprietary License
Classifier: Operating System :: Microsoft :: Windows
Classifier: Operating System :: MacOS
Classifier: Operating System :: POSIX :: Linux
